ocx/OCX_SCHEMA.spp
ocx/OCX_Schema.xsd
ocx/__init__.py
ocx/ocx_286/OCX_Schema.xsd
ocx/ocx_286/__init__.py
ocx/ocx_286/ocx_286.py
ocx/ocx_286/unitsmlSchema_lite-0.9.18.xsd
ocx/ocx_286/xsdata.xml
ocx/ocx_300/OCX_Schema.xsd
ocx/ocx_300/__init__.py
ocx/ocx_300/ocx_300.py
ocx/ocx_300/unitsmlSchema_lite-0.9.18.xsd
ocx/ocx_300/xsdata.xml
ocx/ocx_301/OCX_Schema.xsd
ocx/ocx_301/__init__.py
ocx/ocx_301/ocx_301.py
ocx/ocx_301/unitsmlSchema_lite-0.9.18.xsd
ocx/ocx_301/xsdata.xml
ocx/ocx_310/__init__.py
ocx/ocx_310/ocx_310.py
ocx/ocx_310rc4/__init__.py
ocx/ocx_310rc4/ocx_310rc4.py
ocx/unitsmlSchema_lite-0.9.18.xsd
ocx-3.1.0.dist-info/LICENSE
ocx-3.1.0.dist-info/METADATA
ocx-3.1.0.dist-info/WHEEL
ocx-3.1.0.dist-info/RECORD
