Metadata-Version: 2.3
Name: OCX
Version: 3.1.0
Summary: 
Author: ocastrup
Author-email: ole.christian.astrup@dnv.com
Requires-Python: >=3.9,<4.0
Classifier: Programming Language :: Python :: 3
Classifier: Programming Language :: Python :: 3.9
Classifier: Programming Language :: Python :: 3.10
Classifier: Programming Language :: Python :: 3.11
Classifier: Programming Language :: Python :: 3.12
Classifier: Programming Language :: Python :: 3.13
Requires-Dist: ocx_databinding
Requires-Dist: packaging (>=23.1,<24.0)
Requires-Dist: tbump
Requires-Dist: twine
Project-URL: Bug Tracker, https://github.com/OCXStandard/OCX_Schema/issues
Project-URL: Homepage, https://github.com/OCXStandard/OCX_Schema
